trigger_count/__init__.py
trigger_count/conversion/__init__.py
trigger_count/conversion/daq2frame.py
trigger_count/files.py
trigger_count/junying/__init__.py
trigger_count/junying/arduino.py
trigger_count/kengo/__init__.py
trigger_count/kengo/arduino.py
trigger_count/labjack/__init__.py
trigger_count/labjack/base.py
trigger_count/labjack/counter.py
trigger_count/labjack/daq.py
trigger_count/labjack/gui.py
trigger_count/log.py
trigger_count/session/__init__.py
trigger_count/session/quality.py
trigger_count/session/session.py
trigger_count/session/stim.py
trigger_count/ttl_workaround/__init__.py
trigger_count/ttl_workaround/align.py
trigger_count/ttl_workaround/arduino.py
trigger_count/ttl_workaround/start_gui.py
trigger_count/ttl_workaround/xml.py
trigger_count-0.1.25.dist-info/METADATA
trigger_count-0.1.25.dist-info/WHEEL
trigger_count-0.1.25.dist-info/RECORD
