Metadata-Version: 2.1
Name: trigger-count
Version: 0.1.25
Summary: 
Author: Mathis
Author-email: mathis.bassler@protonmail.com
Requires-Python: >=3.10,<4.0
Classifier: Programming Language :: Python :: 3
Classifier: Programming Language :: Python :: 3.10
Classifier: Programming Language :: Python :: 3.11
Requires-Dist: labjack-ljm (>=1.21.0,<2.0.0)
Requires-Dist: pandas (>=2.0.1,<3.0.0)
Requires-Dist: pyserial (>=3.5,<4.0)
Requires-Dist: tqdm (>=4.65.0,<5.0.0)
